RACER/RACER.py
RACER/__init__.py
RACER/preprocessing.py
RACER/version.py
pyracer-1.2.1.dist-info/LICENSE
pyracer-1.2.1.dist-info/METADATA
pyracer-1.2.1.dist-info/WHEEL
pyracer-1.2.1.dist-info/top_level.txt
pyracer-1.2.1.dist-info/RECORD
