Metadata-Version: 2.1
Name: pyracer
Version: 1.2.1
Summary: Unofficial Python implementation of the RACER classification algorithm.
Home-page: https://github.com/Adversarian/RACER
Author: Arian Tashakkor, Mohammad Safaiyan
Author-email: a77physics@gmail.com
License: MIT
Keywords: machine learning,classification,RACER
Classifier: Programming Language :: Python :: 3
Classifier: License :: OSI Approved :: MIT License
Classifier: Operating System :: OS Independent
Classifier: Development Status :: 4 - Beta
Classifier: Intended Audience :: Developers
Classifier: Topic :: Scientific/Engineering :: Artificial Intelligence
License-File: LICENSE
Requires-Dist: numpy
Requires-Dist: pandas
Requires-Dist: optbinning
Requires-Dist: scikit-learn
